Metadata-Version: 1.0
Name: victor-distributions
Version: 1.11
Summary: Gaussian distributions
Home-page: UNKNOWN
Author: professor_olufemi
Author-email: femiosinkolu@gmail.com
License: UNKNOWN
Platform: UNKNOWN
